{"id": "security", "path": "m:\\OneDrive\\HSG\\Bachelor\\4-semester\\o-o-p\\project\\bibliotek_rest\\security.py", "mtime": 1525777754, "size": 342, "hash": "3ec3147972b5817cd0853c7db696a2d2", "data_mtime": 1525939820, "dependencies": ["werkzeug.security", "models.user", "builtins", "abc", "models", "typing"], "suppressed": [], "child_modules": [], "options": {"disallow_any_expr": false, "follow_imports": "silent", "disallow_subclassing_any": false, "warn_no_return": true, "disallow_untyped_calls": false, "ignore_errors": false, "strict_boolean": false, "show_none_errors": true, "strict_optional_whitelist": null, "platform": "win32", "strict_optional": false, "disallow_any_generics": false, "disallow_any_unimported": false, "no_implicit_optional": false, "disallow_untyped_decorators": false, "warn_unused_ignores": false, "warn_return_any": false, "cache_fine_grained": false, "disallow_untyped_defs": false, "always_false": [], "disallow_any_explicit": false, "follow_imports_for_stubs": false, "check_untyped_defs": false, "ignore_missing_imports": true, "always_true": [], "disallow_any_decorated": false, "quick_and_dirty": false}, "dep_prios": [5, 5, 5, 30, 30, 30], "dep_lines": [1, 2, 1, 1, 1, 1], "interface_hash": "0bafaa30a114b60cbf799290c9d139a7", "version_id": "0.590", "ignore_all": false}
